todoist_digest/__init__.py
todoist_digest/email.py
todoist_digest/patch.py
todoist_digest/templates.py
todoist_digest/todoist.py
todoist_digest/util.py
todoist_digest-0.12.0.dist-info/WHEEL
todoist_digest-0.12.0.dist-info/entry_points.txt
todoist_digest-0.12.0.dist-info/METADATA
todoist_digest-0.12.0.dist-info/RECORD
