Metadata-Version: 2.4
Name: todoist-digest
Version: 0.12.0
Summary: Generate a digest of comments that occurred since the last checked in date. Useful for including in an email.
Keywords: todoist,digest,task,management
Author: Michael Bianco
Author-email: Michael Bianco <mike@mikebian.co>
License-Expression: MIT
Requires-Dist: apscheduler>=3.11.0
Requires-Dist: backoff>=2.2.1
Requires-Dist: click>=8.2.1
Requires-Dist: css-inline>=0.17.0
Requires-Dist: funcy-pipe>=0.11.1
Requires-Dist: jinja2>=3.1.6
Requires-Dist: markdown2>=2.5.4
Requires-Dist: pyjson5>=1.6.9
Requires-Dist: python-dateutil>=2.9.0.post0
Requires-Dist: python-decouple-typed>=3.11.0
Requires-Dist: structlog>=25.4.0
Requires-Dist: structlog-config>=0.1.1
Requires-Dist: todoist-api-python>=3.1.0
Requires-Dist: whatever>=0.7
Requires-Dist: whenever>=0.9.2
Requires-Python: >=3.11
